{
	"$schema": "https://schemas.wp.org/trunk/block.json",
	"apiVersion": 3,
	"name": "wpsp/accordion",
	"version": "0.1.0",
	"title": "Accordion",
	"category": "design",
	"description": "A vertically stacked group of interactive headings that show and hide content.",
	"example": {},
	"supports": {
		"html": false,
		"align": true,
		"color": {
			"background": true,
			"gradient": true
		},
		"spacing": {
			"padding": true,
			"margin": true,
			"blockGap": true
		},
		"layout": true,
		"interactivity": true
	},
	"attributes": {
		"iconPosition": {
			"type": "string",
			"default": "right"
		},
		"allowMultipleOpen": {
			"type": "boolean",
			"default": false
		},
		"allowedBlocks": {
			"type": "array"
		}
	},
	"styles": [
		{
			"name": "default",
			"label": "Default",
			"isDefault": true
		},
		{
			"name": "chevron",
			"label": "Chevron"
		},
		{
			"name": "arrow",
			"label": "Arrow"
		},
		{
			"name": "no-icon",
			"label": "No Icon"
		}
	],
	"allowedBlocks": [ "wpsp/accordion-item" ],
	"textdomain": "accordion",
	"editorScript": "file:./index.js",
	"viewScriptModule": "file:./view.js",
	"render": "file:./render.php",
	"style": "file:./style-index.css"
}
